<?xml version="1.0" encoding="UTF-8"?>
<jcr:root xmlns:sling="http://sling.apache.org/jcr/sling/1.0" xmlns:cq="http://www.day.com/jcr/cq/1.0" xmlns:jcr="http://www.jcp.org/jcr/1.0" xmlns:mix="http://www.jcp.org/jcr/mix/1.0" xmlns:nt="http://www.jcp.org/jcr/nt/1.0"
    jcr:primaryType="cq:Page">
    <jcr:content
        cq:lastModified="{Date}2019-07-25T10:02:24.066-04:00"
        cq:lastModifiedBy="admin"
        cq:lastReplicated="{Date}2019-07-19T10:36:36.431-04:00"
        cq:lastReplicatedBy="admin"
        cq:lastReplicationAction="Activate"
        cq:template="/conf/example/settings/wcm/templates/landing-page-template"
        jcr:isCheckedOut="{Boolean}true"
        jcr:mixinTypes="[mix:versionable]"
        jcr:primaryType="cq:PageContent"
        jcr:title="Electric Cars"
        jcr:uuid="3f5b0783-c69f-4a4a-8a3a-e1bcbdb7c2e1"
        sling:resourceType="example/components/structure/page"
        navTitle="Cars"
        pageTitle="Electric Cars">
        <root
            jcr:primaryType="nt:unstructured"
            sling:resourceType="wcm/foundation/components/responsivegrid">
            <responsivegrid
                jcr:created="{Date}2019-07-17T13:28:02.218-04:00"
                jcr:createdBy="admin"
                jcr:lastModified="{Date}2019-07-17T13:40:48.767-04:00"
                jcr:lastModifiedBy="admin"
                jcr:primaryType="nt:unstructured"
                sling:resourceType="wcm/foundation/components/responsivegrid">
                <responsivegrid
                    cq:styleIds="[1563894265299]"
                    jcr:created="{Date}2019-07-23T13:47:31.129-04:00"
                    jcr:createdBy="admin"
                    jcr:lastModified="{Date}2019-07-23T13:47:31.129-04:00"
                    jcr:lastModifiedBy="admin"
                    jcr:primaryType="nt:unstructured"
                    sling:resourceType="wcm/foundation/components/responsivegrid">
                    <cq:responsive jcr:primaryType="nt:unstructured"/>
                    <teaser
                        cq:styleIds="[1563901716960]"
                        jcr:created="{Date}2019-07-23T13:48:07.647-04:00"
                        jcr:createdBy="admin"
                        jcr:lastModified="{Date}2019-07-25T10:02:14.376-04:00"
                        jcr:lastModifiedBy="admin"
                        jcr:primaryType="nt:unstructured"
                        sling:resourceType="example/components/content/teaser"
                        actionsEnabled="true"
                        descriptionFromPage="true"
                        fileReference="/content/dam/example/tesla_wide.jpg"
                        textIsRich="true"
                        titleFromPage="true">
                        <cq:responsive jcr:primaryType="nt:unstructured">
                            <default
                                jcr:primaryType="nt:unstructured"
                                offset="0"
                                width="12"/>
                        </cq:responsive>
                        <actions jcr:primaryType="nt:unstructured">
                            <item0
                                jcr:primaryType="nt:unstructured"
                                link="/content/example/en/cars/tesla"
                                text="Read More"/>
                        </actions>
                    </teaser>
                    <teaser_293276835
                        cq:styleIds="[1563901716960]"
                        jcr:created="{Date}2019-07-23T13:59:58.797-04:00"
                        jcr:createdBy="admin"
                        jcr:lastModified="{Date}2019-07-25T10:02:24.062-04:00"
                        jcr:lastModifiedBy="admin"
                        jcr:primaryType="nt:unstructured"
                        sling:resourceType="example/components/content/teaser"
                        actionsEnabled="true"
                        descriptionFromPage="true"
                        fileReference="/content/dam/example/etron_wide.jpg"
                        linkURL="/content/example/en/cars/e-tron"
                        textIsRich="true"
                        titleFromPage="true">
                        <cq:responsive jcr:primaryType="nt:unstructured">
                            <default
                                jcr:primaryType="nt:unstructured"
                                offset="0"
                                width="12"/>
                        </cq:responsive>
                        <actions jcr:primaryType="nt:unstructured">
                            <item0
                                jcr:primaryType="nt:unstructured"
                                link="/content/example/en/cars/e-tron"
                                text="Read More"/>
                        </actions>
                    </teaser_293276835>
                    <teaser_990360842
                        cq:styleIds="[1563901716960]"
                        jcr:created="{Date}2019-07-23T14:00:03.016-04:00"
                        jcr:createdBy="admin"
                        jcr:lastModified="{Date}2019-07-23T14:08:00.973-04:00"
                        jcr:lastModifiedBy="admin"
                        jcr:primaryType="nt:unstructured"
                        sling:resourceType="example/components/content/teaser"
                        actionsEnabled="true"
                        descriptionFromPage="true"
                        fileReference="/content/dam/example/leaf.jpg"
                        textIsRich="true"
                        titleFromPage="true">
                        <cq:responsive jcr:primaryType="nt:unstructured">
                            <default
                                jcr:primaryType="nt:unstructured"
                                offset="0"
                                width="12"/>
                        </cq:responsive>
                        <actions jcr:primaryType="nt:unstructured">
                            <item0
                                jcr:primaryType="nt:unstructured"
                                link="/content/example/en/cars/Leaf"
                                text="Read More"/>
                        </actions>
                    </teaser_990360842>
                </responsivegrid>
            </responsivegrid>
        </root>
    </jcr:content>
    <e-tron/>
    <Leaf/>
    <tesla/>
</jcr:root>
